setup.cfg
setup.py
seaborn_meta/__init__.py
seaborn_meta/calling_function.py
seaborn_meta/class_name.py
seaborn_meta/parse_doc.py
seaborn_meta.egg-info/PKG-INFO
seaborn_meta.egg-info/SOURCES.txt
seaborn_meta.egg-info/dependency_links.txt
seaborn_meta.egg-info/requires.txt
seaborn_meta.egg-info/top_level.txt
test/test_calling_function.py
test/test_class_name.py
test/test_parse_doc.py