Metadata-Version: 1.1
Name: seaborn-meta
Version: 1.0.0
Summary: SeabornMeta allows for simple changingof names between conventions, as wellas auto-generating init files
Home-page: https://github.com/SeabornGames/meta
Author: Ben Christenson
Author-email: Python@BenChristenson.com
License: MIT License
Download-URL: https://github.com/SeabornGames/meta/tarball/download
Keywords: meta
Platform: UNKNOWN
Classifier: Intended Audience :: Developers
Classifier: Natural Language :: English
Classifier: License :: Other/Proprietary License
Classifier: Operating System :: POSIX :: Linux
Classifier: Programming Language :: Python
Classifier: Programming Language :: Python :: 2.7
Classifier: Programming Language :: Python :: 3.6
